AsynchronousPS4Controller/Controller.py
AsynchronousPS4Controller/Mapping.py
AsynchronousPS4Controller/__init__.py
AsynchronousPS4Controller-0.1.0.dist-info/LICENSE
AsynchronousPS4Controller-0.1.0.dist-info/METADATA
AsynchronousPS4Controller-0.1.0.dist-info/WHEEL
AsynchronousPS4Controller-0.1.0.dist-info/top_level.txt
AsynchronousPS4Controller-0.1.0.dist-info/RECORD
