Metadata-Version: 2.1
Name: AsynchronousPS4Controller
Version: 0.1.0
Summary: A package to suit your non-blocking PS4 interface
Home-page: https://github.com/GeomKid/AsyncPyPS4Controller
Author: Tan Chin Peng
Author-email: huntiktan188@gmail.com
Classifier: Intended Audience :: Developers
Classifier: Programming Language :: Python :: 3.9
Classifier: Programming Language :: Python :: 3.10
Classifier: Programming Language :: Python :: 3.11
Classifier: License :: OSI Approved :: MIT License
Classifier: Operating System :: POSIX :: Linux
Classifier: Topic :: Software Development :: Libraries
Classifier: Topic :: Software Development :: Libraries :: Python Modules
Classifier: Topic :: Utilities
Requires-Python: >=3.9
License-File: LICENSE
Requires-Dist: aiofiles >=23.1.0
Requires-Dist: tomli
